setup.py
coinwraps/__init__.py
coinwraps/base.py
coinwraps/bithumb.py
coinwraps/bittrex.py
coinwraps/coinone.py
coinwraps/config.py
coinwraps/korbit.py
coinwraps/poloniex.py
coinwraps/typing.py
coinwraps/upbit.py
coinwraps.egg-info/PKG-INFO
coinwraps.egg-info/SOURCES.txt
coinwraps.egg-info/dependency_links.txt
coinwraps.egg-info/requires.txt
coinwraps.egg-info/top_level.txt