Metadata-Version: 1.1
Name: coinwraps
Version: 0.0.8
Summary: coinwraps
Home-page: https://github.com/youknowone/coinwraps
Author: Jeong YunWon
Author-email: coinwraps@youknowone.org
License: UNKNOWN
Platform: UNKNOWN
Classifier: Intended Audience :: Developers
Classifier: Operating System :: OS Independent
Classifier: License :: OSI Approved :: BSD License
Classifier: Programming Language :: Python :: 3
Classifier: Programming Language :: Python :: 3.6
